vcdisk.py
vcdisk-0.3.1.dist-info/LICENSE
vcdisk-0.3.1.dist-info/METADATA
vcdisk-0.3.1.dist-info/WHEEL
vcdisk-0.3.1.dist-info/top_level.txt
vcdisk-0.3.1.dist-info/RECORD
