Metadata-Version: 2.1
Name: vcdisk
Version: 0.3.1
Summary: Circular velocities of thick galaxy disks
Author-email: Lorenzo Posti <lorenzo.posti@gmail.com>
License: BSD-2
Project-URL: homepage, https://github.com/lposti/vcdisk
Project-URL: documentation, https://vcdisk.readthedocs.io/en/latest/
Classifier: License :: OSI Approved :: BSD License
Classifier: Programming Language :: Python
License-File: LICENSE
Requires-Dist: numpy
Requires-Dist: scipy
Requires-Dist: jinja2 (==3.0.3)
